rensis/__init__.py
rensis/core.py
rensis/data/stubid.yar
rensis-1.0.5.dist-info/METADATA
rensis-1.0.5.dist-info/WHEEL
rensis-1.0.5.dist-info/top_level.txt
rensis-1.0.5.dist-info/RECORD
