Metadata-Version: 2.2
Name: rensis
Version: 1.0.5
Requires-Python: >=3.11
Requires-Dist: nsisunbz2
Requires-Dist: pefile
Requires-Dist: yara-python
